{
  "batch": "FARM-4B",
  "change_type": "medical_editorial",
  "expected_version": "12.66",
  "allowed_files": [
    "data/refs.js",
    "data/topics.js",
    "docs/editorial/review-batches/FARM-4B.json",
    "index.html",
    "sw.js",
    "version.json"
  ],
  "questions": {
    "0b5ea123": {
      "action": "rebuild",
      "preserve_fsrs": true,
      "editorial_gate": {
        "evidence": "VERIFICADA",
        "pending": "NENHUMA",
        "score": "18/20",
        "verdict": "aprovada",
        "publication": "LIBERADA"
      }
    }
  },
  "expected_question_delta": 0,
  "refs_policy": "declared",
  "references": {
    "cni_nephrotoxicity_naesens": "add",
    "banff_2019_kidney_meeting": "add"
  },
  "external_review": {
    "greptile": "unavailable",
    "fallback_reviewer": "Codex — revisar-nefroquest"
  }
}
